LICENSE
README.md
setup.cfg
setup.py
LINUX_SGIO.egg-info/PKG-INFO
LINUX_SGIO.egg-info/SOURCES.txt
LINUX_SGIO.egg-info/dependency_links.txt
LINUX_SGIO.egg-info/top_level.txt
linux_sgio/__init__.py
linux_sgio/sgiomodule.c