Metadata-Version: 1.0
Name: LINUX-SGIO
Version: 1.1
Summary: Module for calling Linux SG_IO devices
Home-page: UNKNOWN
Author: Ronnie Sahlberg
Author-email: ronniesahlberg@gmail.com
License: LGPLv2.1
Platform: UNKNOWN
